[{"id":"663455","date":"2022-05-08","psi":null,"clw":null,"velo":null,"vaa":null,"n":73},{"id":"663455","date":"2022-05-26","psi":null,"clw":null,"velo":null,"vaa":null,"n":156},{"id":"663455","date":"2022-06-01","psi":109.9,"clw":0.1566,"velo":93.4,"vaa":-5.19,"n":243},{"id":"663455","date":"2022-06-09","psi":114.8,"clw":0.164,"velo":94.7,"vaa":-5.29,"n":334},{"id":"663455","date":"2022-06-15","psi":108.4,"clw":0.1468,"velo":94.5,"vaa":-5.27,"n":419},{"id":"663455","date":"2022-06-28","psi":105.9,"clw":0.1396,"velo":94.5,"vaa":-5.26,"n":488},{"id":"663455","date":"2022-07-04","psi":105.3,"clw":0.1388,"velo":94.3,"vaa":-5.24,"n":580},{"id":"663455","date":"2022-07-12","psi":102.0,"clw":0.1286,"velo":94.5,"vaa":-5.22,"n":659},{"id":"663455","date":"2022-07-23","psi":101.1,"clw":0.1267,"velo":94.4,"vaa":-5.21,"n":749},{"id":"663455","date":"2022-09-12","psi":99.1,"clw":0.1218,"velo":94.2,"vaa":-5.17,"n":873},{"id":"663455","date":"2022-09-17","psi":97.9,"clw":0.1184,"velo":94.3,"vaa":-5.13,"n":958}]