[{"id":"663623","date":"2023-05-03","psi":null,"clw":null,"velo":null,"vaa":null,"n":0},{"id":"663623","date":"2023-05-08","psi":null,"clw":null,"velo":null,"vaa":null,"n":81},{"id":"663623","date":"2023-05-14","psi":null,"clw":null,"velo":null,"vaa":null,"n":173},{"id":"663623","date":"2023-05-19","psi":84.6,"clw":0.0675,"velo":95.2,"vaa":-5.6,"n":263},{"id":"663623","date":"2023-05-25","psi":84.4,"clw":0.0582,"velo":95.1,"vaa":-5.58,"n":338},{"id":"663623","date":"2023-05-30","psi":84.5,"clw":0.0608,"velo":95.1,"vaa":-5.65,"n":414},{"id":"663623","date":"2023-06-06","psi":84.6,"clw":0.0692,"velo":95.1,"vaa":-5.66,"n":508},{"id":"663623","date":"2023-06-17","psi":84.7,"clw":0.0623,"velo":95.2,"vaa":-5.66,"n":591},{"id":"663623","date":"2023-06-22","psi":85.2,"clw":0.058,"velo":95.4,"vaa":-5.71,"n":679},{"id":"663623","date":"2023-06-27","psi":85.8,"clw":0.0665,"velo":95.8,"vaa":-5.68,"n":766},{"id":"663623","date":"2023-07-03","psi":85.9,"clw":0.0667,"velo":95.9,"vaa":-5.62,"n":859},{"id":"663623","date":"2023-07-08","psi":86.5,"clw":0.0636,"velo":96.2,"vaa":-5.64,"n":948},{"id":"663623","date":"2023-07-15","psi":86.7,"clw":0.0646,"velo":96.4,"vaa":-5.62,"n":1000},{"id":"663623","date":"2023-07-21","psi":86.8,"clw":0.0657,"velo":96.4,"vaa":-5.67,"n":1000},{"id":"663623","date":"2023-07-26","psi":86.7,"clw":0.0681,"velo":96.4,"vaa":-5.6,"n":1000},{"id":"663623","date":"2023-07-31","psi":87.1,"clw":0.0746,"velo":96.4,"vaa":-5.55,"n":1000},{"id":"663623","date":"2023-08-06","psi":86.6,"clw":0.0731,"velo":96.5,"vaa":-5.5,"n":1000},{"id":"663623","date":"2023-08-12","psi":87.6,"clw":0.0747,"velo":96.8,"vaa":-5.46,"n":1000},{"id":"663623","date":"2023-08-19","psi":89.7,"clw":0.0803,"velo":96.9,"vaa":-5.46,"n":1000},{"id":"663623","date":"2023-08-26","psi":92.7,"clw":0.0887,"velo":97.0,"vaa":-5.41,"n":1000},{"id":"663623","date":"2023-09-01","psi":91.5,"clw":0.0851,"velo":97.0,"vaa":-5.42,"n":1000},{"id":"663623","date":"2023-09-09","psi":92.9,"clw":0.0893,"velo":97.0,"vaa":-5.4,"n":1000},{"id":"663623","date":"2023-09-15","psi":94.1,"clw":0.0927,"velo":97.0,"vaa":-5.37,"n":1000},{"id":"663623","date":"2023-09-21","psi":96.4,"clw":0.0997,"velo":97.0,"vaa":-5.33,"n":1000},{"id":"663623","date":"2024-03-31","psi":95.3,"clw":0.0965,"velo":97.0,"vaa":-5.31,"n":1000},{"id":"663623","date":"2024-04-06","psi":94.4,"clw":0.0934,"velo":97.1,"vaa":-5.37,"n":1000},{"id":"663623","date":"2024-04-12","psi":94.6,"clw":0.0935,"velo":97.1,"vaa":-5.44,"n":1000},{"id":"663623","date":"2024-04-17","psi":95.1,"clw":0.0948,"velo":97.1,"vaa":-5.44,"n":1000},{"id":"663623","date":"2024-04-24","psi":96.9,"clw":0.1015,"velo":96.8,"vaa":-5.43,"n":1000},{"id":"663623","date":"2024-04-29","psi":96.9,"clw":0.1022,"velo":96.7,"vaa":-5.4,"n":1000},{"id":"663623","date":"2024-05-04","psi":92.9,"clw":0.0911,"velo":96.6,"vaa":-5.4,"n":1000},{"id":"663623","date":"2024-05-11","psi":91.6,"clw":0.0876,"velo":96.5,"vaa":-5.46,"n":1000},{"id":"663623","date":"2024-05-17","psi":93.7,"clw":0.0941,"velo":96.4,"vaa":-5.47,"n":1000},{"id":"663623","date":"2024-05-22","psi":93.7,"clw":0.0945,"velo":96.3,"vaa":-5.48,"n":1000},{"id":"663623","date":"2024-05-28","psi":93.2,"clw":0.0935,"velo":96.2,"vaa":-5.5,"n":1000},{"id":"663623","date":"2024-06-02","psi":96.5,"clw":0.1033,"velo":96.1,"vaa":-5.49,"n":1000},{"id":"663623","date":"2024-06-07","psi":96.6,"clw":0.1046,"velo":96.0,"vaa":-5.43,"n":1000},{"id":"663623","date":"2024-06-12","psi":99.0,"clw":0.1118,"velo":96.0,"vaa":-5.34,"n":1000},{"id":"663623","date":"2024-06-18","psi":96.7,"clw":0.1056,"velo":96.0,"vaa":-5.32,"n":1000},{"id":"663623","date":"2024-06-23","psi":93.8,"clw":0.0992,"velo":95.6,"vaa":-5.3,"n":1000},{"id":"663623","date":"2024-06-29","psi":100.4,"clw":0.1183,"velo":95.6,"vaa":-5.27,"n":1000},{"id":"663623","date":"2024-07-04","psi":101.2,"clw":0.1216,"velo":95.5,"vaa":-5.21,"n":1000},{"id":"663623","date":"2024-07-09","psi":103.4,"clw":0.1283,"velo":95.5,"vaa":-5.13,"n":1000},{"id":"663623","date":"2024-07-14","psi":102.0,"clw":0.125,"velo":95.4,"vaa":-5.1,"n":1000},{"id":"663623","date":"2024-07-21","psi":100.5,"clw":0.1214,"velo":95.3,"vaa":-5.08,"n":1000},{"id":"663623","date":"2024-07-27","psi":99.8,"clw":0.1194,"velo":95.3,"vaa":-5.07,"n":1000},{"id":"663623","date":"2024-08-02","psi":97.8,"clw":0.1138,"velo":95.3,"vaa":-5.03,"n":1000},{"id":"663623","date":"2024-08-07","psi":95.9,"clw":0.1084,"velo":95.3,"vaa":-5.04,"n":1000},{"id":"663623","date":"2024-08-13","psi":95.7,"clw":0.1077,"velo":95.3,"vaa":-5.04,"n":1000},{"id":"663623","date":"2024-08-18","psi":97.3,"clw":0.1111,"velo":95.5,"vaa":-5.09,"n":1000},{"id":"663623","date":"2024-08-24","psi":94.9,"clw":0.1043,"velo":95.5,"vaa":-5.07,"n":1000},{"id":"663623","date":"2024-08-30","psi":91.7,"clw":0.0947,"velo":95.5,"vaa":-5.14,"n":1000},{"id":"663623","date":"2024-09-05","psi":90.4,"clw":0.0915,"velo":95.3,"vaa":-5.21,"n":1000},{"id":"663623","date":"2024-09-11","psi":90.5,"clw":0.0913,"velo":95.4,"vaa":-5.24,"n":1000},{"id":"663623","date":"2024-09-16","psi":92.3,"clw":0.0955,"velo":95.5,"vaa":-5.26,"n":1000},{"id":"663623","date":"2024-09-22","psi":91.9,"clw":0.0935,"velo":95.7,"vaa":-5.26,"n":1000},{"id":"663623","date":"2024-09-29","psi":91.0,"clw":0.0909,"velo":95.7,"vaa":-5.29,"n":1000},{"id":"663623","date":"2025-03-29","psi":92.2,"clw":0.0942,"velo":95.7,"vaa":-5.33,"n":1000},{"id":"663623","date":"2025-04-04","psi":92.2,"clw":0.0939,"velo":95.7,"vaa":-5.38,"n":1000},{"id":"663623","date":"2025-04-09","psi":92.9,"clw":0.0955,"velo":95.7,"vaa":-5.46,"n":1000},{"id":"663623","date":"2025-04-15","psi":92.1,"clw":0.0941,"velo":95.5,"vaa":-5.45,"n":1000},{"id":"663623","date":"2025-04-20","psi":92.2,"clw":0.0944,"velo":95.4,"vaa":-5.48,"n":1000},{"id":"663623","date":"2025-04-25","psi":95.6,"clw":0.1039,"velo":95.5,"vaa":-5.5,"n":1000},{"id":"663623","date":"2025-04-30","psi":97.1,"clw":0.1083,"velo":95.5,"vaa":-5.46,"n":1000},{"id":"663623","date":"2025-05-06","psi":95.5,"clw":0.1036,"velo":95.5,"vaa":-5.46,"n":1000},{"id":"663623","date":"2025-05-12","psi":91.9,"clw":0.094,"velo":95.3,"vaa":-5.49,"n":1000},{"id":"663623","date":"2025-05-17","psi":88.7,"clw":0.0875,"velo":94.7,"vaa":-5.57,"n":1000},{"id":"663623","date":"2025-05-24","psi":87.2,"clw":0.0852,"velo":94.2,"vaa":-5.61,"n":1000},{"id":"663623","date":"2025-05-30","psi":87.5,"clw":0.0869,"velo":94.1,"vaa":-5.59,"n":1000},{"id":"663623","date":"2025-06-05","psi":85.9,"clw":0.0828,"velo":94.0,"vaa":-5.56,"n":1000},{"id":"663623","date":"2025-06-11","psi":86.1,"clw":0.0831,"velo":94.1,"vaa":-5.53,"n":1000},{"id":"663623","date":"2025-06-16","psi":86.2,"clw":0.0829,"velo":94.2,"vaa":-5.55,"n":1000},{"id":"663623","date":"2025-06-21","psi":84.5,"clw":0.078,"velo":94.2,"vaa":-5.52,"n":1000},{"id":"663623","date":"2025-06-27","psi":84.7,"clw":0.0787,"velo":94.2,"vaa":-5.5,"n":1000},{"id":"663623","date":"2025-07-03","psi":82.7,"clw":0.0727,"velo":94.2,"vaa":-5.51,"n":1000},{"id":"663623","date":"2025-07-08","psi":83.9,"clw":0.0768,"velo":94.2,"vaa":-5.45,"n":1000},{"id":"663623","date":"2025-07-13","psi":85.0,"clw":0.0802,"velo":94.2,"vaa":-5.41,"n":1000},{"id":"663623","date":"2025-07-21","psi":85.1,"clw":0.0799,"velo":94.3,"vaa":-5.41,"n":1000},{"id":"663623","date":"2025-07-27","psi":86.6,"clw":0.0843,"velo":94.3,"vaa":-5.43,"n":1000},{"id":"663623","date":"2025-08-02","psi":85.7,"clw":0.081,"velo":94.4,"vaa":-5.45,"n":1000},{"id":"663623","date":"2025-08-08","psi":86.8,"clw":0.084,"velo":94.4,"vaa":-5.5,"n":1000},{"id":"663623","date":"2025-08-13","psi":87.7,"clw":0.0865,"velo":94.4,"vaa":-5.5,"n":1000},{"id":"663623","date":"2025-08-19","psi":85.9,"clw":0.0819,"velo":94.3,"vaa":-5.47,"n":1000},{"id":"663623","date":"2025-08-24","psi":84.9,"clw":0.0791,"velo":94.3,"vaa":-5.49,"n":1000},{"id":"663623","date":"2025-08-30","psi":83.9,"clw":0.0758,"velo":94.3,"vaa":-5.52,"n":1000},{"id":"663623","date":"2025-09-05","psi":84.2,"clw":0.0763,"velo":94.4,"vaa":-5.52,"n":1000},{"id":"663623","date":"2025-09-10","psi":84.1,"clw":0.0761,"velo":94.4,"vaa":-5.51,"n":1000},{"id":"663623","date":"2025-09-16","psi":85.8,"clw":0.0808,"velo":94.4,"vaa":-5.56,"n":1000},{"id":"663623","date":"2025-09-21","psi":86.4,"clw":0.0822,"velo":94.5,"vaa":-5.51,"n":1000},{"id":"663623","date":"2025-09-27","psi":87.2,"clw":0.0836,"velo":94.7,"vaa":-5.46,"n":1000},{"id":"663623","date":"2026-03-29","psi":88.3,"clw":0.0872,"velo":94.7,"vaa":-5.43,"n":1000},{"id":"663623","date":"2026-04-04","psi":90.2,"clw":0.0926,"velo":94.7,"vaa":-5.4,"n":1000},{"id":"663623","date":"2026-04-10","psi":91.9,"clw":0.0976,"velo":94.8,"vaa":-5.34,"n":1000},{"id":"663623","date":"2026-04-15","psi":89.9,"clw":0.092,"velo":94.8,"vaa":-5.3,"n":1000},{"id":"663623","date":"2026-04-20","psi":92.4,"clw":0.0985,"velo":94.9,"vaa":-5.33,"n":1000},{"id":"663623","date":"2026-04-25","psi":92.8,"clw":0.0999,"velo":94.9,"vaa":-5.31,"n":1000},{"id":"663623","date":"2026-05-01","psi":96.0,"clw":0.1097,"velo":94.8,"vaa":-5.28,"n":1000},{"id":"663623","date":"2026-05-07","psi":94.3,"clw":0.1046,"velo":94.8,"vaa":-5.3,"n":1000},{"id":"663623","date":"2026-05-13","psi":94.0,"clw":0.1037,"velo":94.8,"vaa":-5.32,"n":1000},{"id":"663623","date":"2026-05-18","psi":93.7,"clw":0.1029,"velo":94.7,"vaa":-5.34,"n":1000},{"id":"663623","date":"2026-05-23","psi":95.9,"clw":0.1089,"velo":94.8,"vaa":-5.35,"n":1000}]