[{"id":"666120","date":"2020-08-26","psi":null,"clw":null,"velo":null,"vaa":null,"n":0},{"id":"666120","date":"2020-09-01","psi":null,"clw":null,"velo":null,"vaa":null,"n":90},{"id":"666120","date":"2020-09-07","psi":null,"clw":null,"velo":null,"vaa":null,"n":186},{"id":"666120","date":"2020-09-12","psi":107.1,"clw":0.1372,"velo":95.8,"vaa":-5.16,"n":269},{"id":"666120","date":"2020-09-19","psi":108.5,"clw":0.1422,"velo":95.8,"vaa":-5.02,"n":368},{"id":"666120","date":"2020-09-24","psi":108.4,"clw":0.1429,"velo":95.8,"vaa":-4.87,"n":467},{"id":"666120","date":"2021-04-04","psi":105.7,"clw":0.1346,"velo":95.7,"vaa":-5.0,"n":571},{"id":"666120","date":"2021-04-10","psi":106.6,"clw":0.137,"velo":95.7,"vaa":-5.03,"n":659},{"id":"666120","date":"2021-04-15","psi":105.1,"clw":0.1327,"velo":95.7,"vaa":-5.07,"n":748},{"id":"666120","date":"2021-04-21","psi":105.8,"clw":0.1349,"velo":95.7,"vaa":-5.04,"n":846},{"id":"666120","date":"2021-04-27","psi":104.6,"clw":0.1315,"velo":95.7,"vaa":-5.02,"n":943},{"id":"666120","date":"2021-05-02","psi":106.1,"clw":0.1356,"velo":95.8,"vaa":-4.99,"n":1000},{"id":"666120","date":"2021-05-08","psi":108.0,"clw":0.1408,"velo":95.8,"vaa":-5.01,"n":1000},{"id":"666120","date":"2021-05-15","psi":106.3,"clw":0.1357,"velo":95.8,"vaa":-5.05,"n":1000},{"id":"666120","date":"2021-05-21","psi":105.0,"clw":0.1315,"velo":95.9,"vaa":-5.06,"n":1000},{"id":"666120","date":"2021-05-29","psi":105.5,"clw":0.1312,"velo":96.1,"vaa":-5.16,"n":1000},{"id":"666120","date":"2021-06-04","psi":103.6,"clw":0.1258,"velo":96.1,"vaa":-5.15,"n":1000},{"id":"666120","date":"2021-06-10","psi":106.2,"clw":0.1328,"velo":96.2,"vaa":-5.14,"n":1000},{"id":"666120","date":"2021-06-16","psi":104.5,"clw":0.1282,"velo":96.2,"vaa":-5.12,"n":1000},{"id":"666120","date":"2021-06-21","psi":105.1,"clw":0.1298,"velo":96.2,"vaa":-5.11,"n":1000},{"id":"666120","date":"2021-06-26","psi":104.6,"clw":0.1285,"velo":96.2,"vaa":-5.12,"n":1000},{"id":"666120","date":"2021-07-01","psi":106.4,"clw":0.1328,"velo":96.3,"vaa":-5.16,"n":1000},{"id":"666120","date":"2021-07-06","psi":103.8,"clw":0.1253,"velo":96.3,"vaa":-5.19,"n":1000},{"id":"666120","date":"2021-07-11","psi":101.8,"clw":0.1197,"velo":96.3,"vaa":-5.14,"n":1000},{"id":"666120","date":"2021-08-29","psi":102.1,"clw":0.1206,"velo":96.3,"vaa":-5.12,"n":1000},{"id":"666120","date":"2021-09-04","psi":101.7,"clw":0.1193,"velo":96.3,"vaa":-5.14,"n":1000},{"id":"666120","date":"2021-09-10","psi":100.0,"clw":0.1147,"velo":96.3,"vaa":-5.14,"n":1000},{"id":"666120","date":"2021-09-17","psi":102.6,"clw":0.1224,"velo":96.2,"vaa":-5.18,"n":1000},{"id":"666120","date":"2021-09-22","psi":102.2,"clw":0.1214,"velo":96.2,"vaa":-5.16,"n":1000},{"id":"666120","date":"2021-09-30","psi":104.7,"clw":0.1285,"velo":96.2,"vaa":-5.17,"n":1000},{"id":"666120","date":"2022-04-10","psi":101.7,"clw":0.1202,"velo":96.1,"vaa":-5.16,"n":1000},{"id":"666120","date":"2022-04-16","psi":101.0,"clw":0.1189,"velo":96.0,"vaa":-5.14,"n":1000},{"id":"666120","date":"2022-04-23","psi":103.9,"clw":0.128,"velo":95.9,"vaa":-5.11,"n":1000},{"id":"666120","date":"2022-04-29","psi":103.8,"clw":0.1293,"velo":95.6,"vaa":-5.1,"n":1000},{"id":"666120","date":"2022-05-04","psi":104.0,"clw":0.1312,"velo":95.2,"vaa":-5.12,"n":1000},{"id":"666120","date":"2022-05-11","psi":103.1,"clw":0.13,"velo":95.0,"vaa":-5.12,"n":1000},{"id":"666120","date":"2022-05-16","psi":102.0,"clw":0.1277,"velo":94.8,"vaa":-5.13,"n":1000},{"id":"666120","date":"2022-05-22","psi":103.4,"clw":0.1315,"velo":94.9,"vaa":-5.1,"n":1000},{"id":"666120","date":"2022-05-27","psi":100.6,"clw":0.124,"velo":94.8,"vaa":-5.08,"n":1000},{"id":"666120","date":"2022-06-02","psi":99.7,"clw":0.1202,"velo":95.0,"vaa":-5.1,"n":1000},{"id":"666120","date":"2022-06-08","psi":99.8,"clw":0.1202,"velo":95.0,"vaa":-5.15,"n":1000},{"id":"666120","date":"2022-06-13","psi":101.6,"clw":0.1253,"velo":95.0,"vaa":-5.2,"n":1000},{"id":"666120","date":"2022-06-19","psi":101.5,"clw":0.1239,"velo":95.1,"vaa":-5.26,"n":1000},{"id":"666120","date":"2022-06-24","psi":99.2,"clw":0.1168,"velo":95.2,"vaa":-5.29,"n":1000},{"id":"666120","date":"2022-06-30","psi":100.0,"clw":0.119,"velo":95.2,"vaa":-5.3,"n":1000},{"id":"666120","date":"2022-07-05","psi":100.4,"clw":0.12,"velo":95.2,"vaa":-5.31,"n":1000},{"id":"666120","date":"2022-07-10","psi":100.3,"clw":0.119,"velo":95.3,"vaa":-5.36,"n":1000},{"id":"666120","date":"2022-07-15","psi":102.0,"clw":0.124,"velo":95.3,"vaa":-5.35,"n":1000},{"id":"666120","date":"2022-07-24","psi":103.0,"clw":0.1272,"velo":95.3,"vaa":-5.29,"n":1000},{"id":"666120","date":"2022-07-30","psi":100.9,"clw":0.1209,"velo":95.3,"vaa":-5.33,"n":1000},{"id":"666120","date":"2022-08-05","psi":104.1,"clw":0.1301,"velo":95.3,"vaa":-5.33,"n":1000},{"id":"666120","date":"2022-08-13","psi":103.3,"clw":0.1279,"velo":95.3,"vaa":-5.3,"n":1000}]