[{"id":"681857","date":"2023-06-02","psi":null,"clw":null,"velo":null,"vaa":null,"n":0},{"id":"681857","date":"2023-06-08","psi":null,"clw":null,"velo":null,"vaa":null,"n":89},{"id":"681857","date":"2023-06-14","psi":null,"clw":null,"velo":null,"vaa":null,"n":164},{"id":"681857","date":"2023-06-19","psi":95.0,"clw":0.096,"velo":96.6,"vaa":-5.61,"n":253},{"id":"681857","date":"2023-06-24","psi":101.0,"clw":0.1143,"velo":96.4,"vaa":-5.58,"n":353},{"id":"681857","date":"2023-07-04","psi":103.0,"clw":0.1206,"velo":96.3,"vaa":-5.58,"n":482},{"id":"681857","date":"2023-07-16","psi":102.3,"clw":0.1184,"velo":96.3,"vaa":-5.59,"n":572},{"id":"681857","date":"2023-07-21","psi":104.4,"clw":0.1243,"velo":96.3,"vaa":-5.61,"n":647},{"id":"681857","date":"2023-07-28","psi":104.3,"clw":0.1245,"velo":96.3,"vaa":-5.55,"n":742},{"id":"681857","date":"2023-08-04","psi":101.8,"clw":0.1175,"velo":96.2,"vaa":-5.57,"n":830},{"id":"681857","date":"2023-08-10","psi":101.8,"clw":0.1181,"velo":96.2,"vaa":-5.52,"n":922},{"id":"681857","date":"2023-08-16","psi":103.0,"clw":0.1224,"velo":96.0,"vaa":-5.51,"n":1000},{"id":"681857","date":"2023-08-22","psi":101.8,"clw":0.1188,"velo":96.0,"vaa":-5.56,"n":1000},{"id":"681857","date":"2023-08-28","psi":102.3,"clw":0.1202,"velo":96.0,"vaa":-5.55,"n":1000},{"id":"681857","date":"2023-09-02","psi":107.7,"clw":0.1355,"velo":95.9,"vaa":-5.64,"n":1000},{"id":"681857","date":"2023-09-08","psi":105.9,"clw":0.1303,"velo":95.9,"vaa":-5.67,"n":1000},{"id":"681857","date":"2023-09-14","psi":104.5,"clw":0.1261,"velo":95.9,"vaa":-5.68,"n":1000},{"id":"681857","date":"2023-09-20","psi":101.9,"clw":0.1193,"velo":95.8,"vaa":-5.66,"n":1000},{"id":"681857","date":"2023-09-26","psi":100.5,"clw":0.1156,"velo":95.7,"vaa":-5.69,"n":1000},{"id":"681857","date":"2024-04-01","psi":103.1,"clw":0.1228,"velo":95.7,"vaa":-5.73,"n":1000},{"id":"681857","date":"2024-04-08","psi":105.2,"clw":0.1281,"velo":95.8,"vaa":-5.76,"n":1000},{"id":"681857","date":"2024-04-15","psi":105.1,"clw":0.1278,"velo":95.7,"vaa":-5.85,"n":1000},{"id":"681857","date":"2024-04-20","psi":107.0,"clw":0.1331,"velo":95.7,"vaa":-5.86,"n":1000},{"id":"681857","date":"2024-04-26","psi":105.8,"clw":0.13,"velo":95.7,"vaa":-5.83,"n":1000},{"id":"681857","date":"2024-05-03","psi":105.4,"clw":0.1292,"velo":95.6,"vaa":-5.85,"n":1000},{"id":"681857","date":"2024-05-08","psi":102.0,"clw":0.1194,"velo":95.6,"vaa":-5.88,"n":1000},{"id":"681857","date":"2024-05-14","psi":102.1,"clw":0.1197,"velo":95.6,"vaa":-5.87,"n":1000},{"id":"681857","date":"2024-05-20","psi":104.7,"clw":0.1269,"velo":95.6,"vaa":-5.92,"n":1000},{"id":"681857","date":"2024-05-25","psi":105.6,"clw":0.1293,"velo":95.6,"vaa":-5.95,"n":1000},{"id":"681857","date":"2024-06-01","psi":104.7,"clw":0.1268,"velo":95.5,"vaa":-5.98,"n":1000},{"id":"681857","date":"2024-06-07","psi":103.3,"clw":0.1229,"velo":95.5,"vaa":-6.0,"n":1000},{"id":"681857","date":"2024-06-12","psi":103.2,"clw":0.1232,"velo":95.4,"vaa":-5.96,"n":1000},{"id":"681857","date":"2024-06-17","psi":103.9,"clw":0.125,"velo":95.4,"vaa":-5.98,"n":1000},{"id":"681857","date":"2024-06-23","psi":102.7,"clw":0.1214,"velo":95.3,"vaa":-6.06,"n":1000},{"id":"681857","date":"2024-06-29","psi":102.9,"clw":0.1216,"velo":95.4,"vaa":-6.09,"n":1000},{"id":"681857","date":"2024-07-05","psi":106.0,"clw":0.1305,"velo":95.4,"vaa":-6.09,"n":1000},{"id":"681857","date":"2024-07-10","psi":109.6,"clw":0.1406,"velo":95.4,"vaa":-6.12,"n":1000},{"id":"681857","date":"2024-09-16","psi":107.3,"clw":0.1346,"velo":95.3,"vaa":-6.09,"n":1000},{"id":"681857","date":"2024-09-21","psi":107.5,"clw":0.1346,"velo":95.4,"vaa":-6.11,"n":1000},{"id":"681857","date":"2024-09-26","psi":108.8,"clw":0.1377,"velo":95.5,"vaa":-6.11,"n":1000},{"id":"681857","date":"2025-03-29","psi":109.7,"clw":0.141,"velo":95.4,"vaa":-6.07,"n":1000},{"id":"681857","date":"2025-04-05","psi":107.9,"clw":0.1348,"velo":95.7,"vaa":-6.05,"n":1000},{"id":"681857","date":"2025-04-11","psi":106.7,"clw":0.1315,"velo":95.6,"vaa":-6.07,"n":1000},{"id":"681857","date":"2025-04-17","psi":104.7,"clw":0.1245,"velo":95.9,"vaa":-6.06,"n":1000},{"id":"681857","date":"2025-04-23","psi":104.9,"clw":0.1262,"velo":95.8,"vaa":-5.96,"n":1000},{"id":"681857","date":"2025-04-29","psi":106.6,"clw":0.1303,"velo":96.0,"vaa":-5.92,"n":1000},{"id":"681857","date":"2025-05-04","psi":108.6,"clw":0.1361,"velo":96.0,"vaa":-5.9,"n":1000},{"id":"681857","date":"2025-05-11","psi":109.9,"clw":0.1399,"velo":96.0,"vaa":-5.88,"n":1000},{"id":"681857","date":"2025-05-17","psi":107.5,"clw":0.1336,"velo":96.0,"vaa":-5.79,"n":1000},{"id":"681857","date":"2025-07-04","psi":110.4,"clw":0.1417,"velo":96.1,"vaa":-5.75,"n":1000},{"id":"681857","date":"2025-07-09","psi":111.9,"clw":0.1464,"velo":96.1,"vaa":-5.71,"n":1000},{"id":"681857","date":"2025-07-18","psi":107.6,"clw":0.134,"velo":96.1,"vaa":-5.67,"n":1000},{"id":"681857","date":"2025-07-24","psi":109.3,"clw":0.1395,"velo":96.0,"vaa":-5.67,"n":1000}]