[{"id":"683627","date":"2024-04-02","psi":null,"clw":null,"velo":null,"vaa":null,"n":31},{"id":"683627","date":"2024-05-08","psi":86.9,"clw":0.0408,"velo":96.4,"vaa":-5.7,"n":213},{"id":"683627","date":"2024-05-27","psi":86.7,"clw":0.0526,"velo":96.2,"vaa":-5.75,"n":295},{"id":"683627","date":"2024-06-07","psi":86.4,"clw":0.0444,"velo":96.2,"vaa":-5.67,"n":366},{"id":"683627","date":"2024-06-20","psi":86.3,"clw":0.0474,"velo":96.1,"vaa":-5.66,"n":447},{"id":"683627","date":"2024-07-23","psi":86.4,"clw":0.0595,"velo":96.2,"vaa":-5.66,"n":629},{"id":"683627","date":"2024-09-10","psi":86.4,"clw":0.0705,"velo":96.2,"vaa":-5.62,"n":928},{"id":"683627","date":"2025-08-05","psi":92.7,"clw":0.0903,"velo":96.4,"vaa":-5.61,"n":1000},{"id":"683627","date":"2025-08-14","psi":93.6,"clw":0.0929,"velo":96.4,"vaa":-5.61,"n":1000},{"id":"683627","date":"2025-08-19","psi":96.4,"clw":0.1002,"velo":96.5,"vaa":-5.65,"n":1000},{"id":"683627","date":"2025-09-01","psi":96.5,"clw":0.1004,"velo":96.5,"vaa":-5.64,"n":1000}]